{
    "Sequencer": {
        "STATUS": 1.0,
        "STEPS": null
    },
    "SerializeTrack": {
        "VARIATION": 0.0
    },
    "Synth1": {
        "values": [
            {
                "key": "ENGINE",
                "value": 0.0
            },
            {
                "key": "VAL_1",
                "value": -11.0
            },
            {
                "key": "VAL_2",
                "value": 54.0
            },
            {
                "key": "VAL_3",
                "value": 183.0
            },
            {
                "key": "VAL_4",
                "value": 8.099998474121094
            },
            {
                "key": "VAL_5",
                "value": 50.0
            },
            {
                "key": "VAL_6",
                "value": 18.0
            },
            {
                "key": "VAL_7",
                "value": 0.0
            },
            {
                "key": "VAL_8",
                "value": 0.0
            },
            {
                "key": "VAL_9",
                "value": 1.0
            },
            {
                "key": "VAL_10",
                "value": 59.0
            },
            {
                "key": "ATTACK",
                "value": 690.0
            },
            {
                "key": "RELEASE",
                "value": 1140.0
            }
        ]
    },
    "TrackFx": {
        "values": [
            {
                "key": "VOLUME",
                "value": 100.0
            },
            {
                "key": "GAIN",
                "value": 1.0
            }
        ]
    }
}